LICENSE
README.md
setup.py
srctoolkit/JavaAnalysis-1.0-SNAPSHOT.jar
srctoolkit/__init__.py
srctoolkit/action_parser.py
srctoolkit/call_graph_analyzer.py
srctoolkit/code2vec.py
srctoolkit/code_chunker.py
srctoolkit/code_cleaner.py
srctoolkit/code_pos.py
srctoolkit/code_stopwords.py
srctoolkit/code_tokenizer.py
srctoolkit/delimiter.py
srctoolkit/dependency_analyzer.py
srctoolkit/dictionary.py
srctoolkit/lemmatizer.py
srctoolkit/pair_checker.py
srctoolkit/predicates.txt
srctoolkit/verb.txt
srctoolkit/verb_helper.py
srctoolkit.egg-info/PKG-INFO
srctoolkit.egg-info/SOURCES.txt
srctoolkit.egg-info/dependency_links.txt
srctoolkit.egg-info/requires.txt
srctoolkit.egg-info/top_level.txt
srctoolkit/javalang/__init__.py
srctoolkit/javalang/ast.py
srctoolkit/javalang/javadoc.py
srctoolkit/javalang/parse.py
srctoolkit/javalang/parser.py
srctoolkit/javalang/tokenizer.py
srctoolkit/javalang/tree.py
srctoolkit/javalang/util.py
srctoolkit/posse/__init__.py
srctoolkit/posse/candidate_provider.py
srctoolkit/posse/chunker.py
srctoolkit/posse/resource.py
srctoolkit/posse/tagger.py
srctoolkit/posse/corpus/normal.fields
srctoolkit/posse/corpus/normal.methods
srctoolkit/posse/dicts/adjective
srctoolkit/posse/dicts/adverb
srctoolkit/posse/dicts/dictionary-allwords
srctoolkit/posse/dicts/dlist
srctoolkit/posse/dicts/irregV
srctoolkit/posse/dicts/n-abbr
srctoolkit/posse/dicts/norule
srctoolkit/posse/dicts/noun
srctoolkit/posse/dicts/participle
srctoolkit/posse/dicts/preposition
srctoolkit/posse/dicts/pronoun
srctoolkit/posse/dicts/quant
srctoolkit/posse/dicts/verb
srctoolkit/spiral/__init__.py
srctoolkit/spiral/__main__.py
srctoolkit/spiral/__version__.py
srctoolkit/spiral/constants.py
srctoolkit/spiral/frequencies.py
srctoolkit/spiral/ronin.py
srctoolkit/spiral/samurai.py
srctoolkit/spiral/simple_splitters.py
srctoolkit/spiral/utils.py
srctoolkit/spiral/data/README.md
srctoolkit/spiral/data/dictionary.pklz
srctoolkit/spiral/data/frequencies.pklz
test/test_abbr.py
test/test_cg.py
test/test_code2vec.py
test/test_code_pos.py
test/test_delimiter.py
test/test_dependence.py
test/test_javalang.py